dansk.py
dansk-0.1.3.dist-info/DESCRIPTION.rst
dansk-0.1.3.dist-info/METADATA
dansk-0.1.3.dist-info/RECORD
dansk-0.1.3.dist-info/WHEEL
dansk-0.1.3.dist-info/metadata.json
dansk-0.1.3.dist-info/top_level.txt
