Metadata-Version: 2.0
Name: dansk
Version: 0.1.3
Summary: Python, but danish.
Home-page: https://github.com/carlbordum/dansk.py
Author: Carl Bordum Hansen
Author-email: carl@bordum.dk
License: MIT
Platform: any
